<?xml version="1.0" encoding="utf-8" standalone="yes"?>
<schema>
  <tablename>freespace_info_0_8_0</tablename>
  <access_privileges>public=ar</access_privileges>
  <column>
    <name>id</name>
    <type>ulong</type>
  </column>
  <column>
    <name>time</name>
    <type>long</type>
  </column>
  <column>
    <name>revision</name>
    <type>int</type>
  </column>
  <column>
    <name>detection_method</name>
    <type>int</type>
  </column>
  <column>
    <name>detectable_classes</name>
    <type>int</type>
  </column>
  <column>
    <name>vertices_begin_geodetic_srid</name>
    <type>int</type>
  </column>
  <column>
    <name>vertices_begin_latitude</name>
    <type>int</type>
  </column>
  <column>
    <name>vertices_begin_longitude</name>
    <type>int</type>
  </column>
  <column>
    <name>vertices_begin_altitude</name>
    <type>int</type>
  </column>
  <column>
    <name>vertices_begin_projective_srid</name>
    <type>int</type>
  </column>
  <column>
    <name>vertices_begin_prc_x</name>
    <type>int</type>
  </column>
  <column>
    <name>vertices_begin_prc_y</name>
    <type>int</type>
  </column>
  <column>
    <name>vertices_begin_prc_z</name>
    <type>int</type>
  </column>
  <column>
    <name>vertices_begin_crp_id</name>
    <type>int</type>
  </column>
  <column>
    <name>vertices_begin_dx_crp</name>
    <type>int</type>
  </column>
  <column>
    <name>vertices_begin_dy_crp</name>
    <type>int</type>
  </column>
  <column>
    <name>vertices_begin_dh_crp</name>
    <type>int</type>
  </column>
  <column>
    <name>vertices_begin_lane_count</name>
    <type>int</type>
  </column>
  <column>
    <name>vertices_begin_lane_position</name>
    <type>int</type>
  </column>
  <column>
    <name>vertices_begin_lane_lateral_position</name>
    <type>int</type>
  </column>
  <column>
    <name>vertices_begin_crp_id_begin</name>
    <type>int</type>
  </column>
  <column>
    <name>vertices_begin_crp_id_end</name>
    <type>int</type>
  </column>
  <column>
    <name>vertices_begin_lane_vertical_position</name>
    <type>int</type>
  </column>
  <column>
    <name>vertices_begin_lane_id</name>
    <type>ulong</type>
  </column>
  <column>
    <name>vertices_begin_dx_lane</name>
    <type>int</type>
  </column>
  <column>
    <name>vertices_begin_dy_lane</name>
    <type>int</type>
  </column>
  <column>
    <name>vertices_begin_dh_lane</name>
    <type>int</type>
  </column>
  <column>
    <name>vertices_begin_semi_axis_length_major</name>
    <type>int</type>
  </column>
  <column>
    <name>vertices_begin_semi_axis_length_minor</name>
    <type>int</type>
  </column>
  <column>
    <name>vertices_begin_ellipse_orientation</name>
    <type>int</type>
  </column>
  <column>
    <name>vertices_begin_altitude_accuracy</name>
    <type>int</type>
  </column>
  <column>
    <name>vertices_dx_list</name>
    <type>vector(int)</type>
  </column>
  <column>
    <name>vertices_dy_list</name>
    <type>vector(int)</type>
  </column>
  <column>
    <name>position_begin_geodetic_srid</name>
    <type>int</type>
  </column>
  <column>
    <name>position_begin_latitude</name>
    <type>int</type>
  </column>
  <column>
    <name>position_begin_longitude</name>
    <type>int</type>
  </column>
  <column>
    <name>position_begin_altitude</name>
    <type>int</type>
  </column>
  <column>
    <name>position_begin_projective_srid</name>
    <type>int</type>
  </column>
  <column>
    <name>position_begin_prc_x</name>
    <type>int</type>
  </column>
  <column>
    <name>position_begin_prc_y</name>
    <type>int</type>
  </column>
  <column>
    <name>position_begin_prc_z</name>
    <type>int</type>
  </column>
  <column>
    <name>position_begin_crp_id</name>
    <type>int</type>
  </column>
  <column>
    <name>position_begin_dx_crp</name>
    <type>int</type>
  </column>
  <column>
    <name>position_begin_dy_crp</name>
    <type>int</type>
  </column>
  <column>
    <name>position_begin_dh_crp</name>
    <type>int</type>
  </column>
  <column>
    <name>position_begin_lane_count</name>
    <type>int</type>
  </column>
  <column>
    <name>position_begin_lane_position</name>
    <type>int</type>
  </column>
  <column>
    <name>position_begin_lane_lateral_position</name>
    <type>int</type>
  </column>
  <column>
    <name>position_begin_crp_id_begin</name>
    <type>int</type>
  </column>
  <column>
    <name>position_begin_crp_id_end</name>
    <type>int</type>
  </column>
  <column>
    <name>position_begin_lane_vertical_position</name>
    <type>int</type>
  </column>
  <column>
    <name>position_begin_lane_id</name>
    <type>ulong</type>
  </column>
  <column>
    <name>position_begin_dx_lane</name>
    <type>int</type>
  </column>
  <column>
    <name>position_begin_dy_lane</name>
    <type>int</type>
  </column>
  <column>
    <name>position_begin_dh_lane</name>
    <type>int</type>
  </column>
  <column>
    <name>position_begin_semi_axis_length_major</name>
    <type>int</type>
  </column>
  <column>
    <name>position_begin_semi_axis_length_minor</name>
    <type>int</type>
  </column>
  <column>
    <name>position_begin_ellipse_orientation</name>
    <type>int</type>
  </column>
  <column>
    <name>position_begin_altitude_accuracy</name>
    <type>int</type>
  </column>
  <column>
    <name>position_end_geodetic_srid</name>
    <type>int</type>
  </column>
  <column>
    <name>position_end_latitude</name>
    <type>int</type>
  </column>
  <column>
    <name>position_end_longitude</name>
    <type>int</type>
  </column>
  <column>
    <name>position_end_altitude</name>
    <type>int</type>
  </column>
  <column>
    <name>position_end_projective_srid</name>
    <type>int</type>
  </column>
  <column>
    <name>position_end_prc_x</name>
    <type>int</type>
  </column>
  <column>
    <name>position_end_prc_y</name>
    <type>int</type>
  </column>
  <column>
    <name>position_end_prc_z</name>
    <type>int</type>
  </column>
  <column>
    <name>position_end_crp_id</name>
    <type>int</type>
  </column>
  <column>
    <name>position_end_dx_crp</name>
    <type>int</type>
  </column>
  <column>
    <name>position_end_dy_crp</name>
    <type>int</type>
  </column>
  <column>
    <name>position_end_dh_crp</name>
    <type>int</type>
  </column>
  <column>
    <name>position_end_lane_count</name>
    <type>int</type>
  </column>
  <column>
    <name>position_end_lane_position</name>
    <type>int</type>
  </column>
  <column>
    <name>position_end_lane_lateral_position</name>
    <type>int</type>
  </column>
  <column>
    <name>position_end_crp_id_begin</name>
    <type>int</type>
  </column>
  <column>
    <name>position_end_crp_id_end</name>
    <type>int</type>
  </column>
  <column>
    <name>position_end_lane_vertical_position</name>
    <type>int</type>
  </column>
  <column>
    <name>position_end_lane_id</name>
    <type>ulong</type>
  </column>
  <column>
    <name>position_end_dx_lane</name>
    <type>int</type>
  </column>
  <column>
    <name>position_end_dy_lane</name>
    <type>int</type>
  </column>
  <column>
    <name>position_end_dh_lane</name>
    <type>int</type>
  </column>
  <column>
    <name>position_end_semi_axis_length_major</name>
    <type>int</type>
  </column>
  <column>
    <name>position_end_semi_axis_length_minor</name>
    <type>int</type>
  </column>
  <column>
    <name>position_end_ellipse_orientation</name>
    <type>int</type>
  </column>
  <column>
    <name>position_end_altitude_accuracy</name>
    <type>int</type>
  </column>
  <column>
    <name>length_value</name>
    <type>int</type>
  </column>
  <column>
    <name>length_accuracy</name>
    <type>int</type>
  </column>
  <column>
    <name>id_begin</name>
    <type>ulong</type>
  </column>
  <column>
    <name>id_end</name>
    <type>ulong</type>
  </column>
  <column>
    <name>existency</name>
    <type>int</type>
  </column>
  <column>
    <name>minimal_detectable_size</name>
    <type>int</type>
  </column>
  <column>
    <name>information_source_list</name>
    <type>Vector(ulong)</type>
  </column>
</schema>
